py_vallocation-0.3.1.dist-info/licenses/LICENSE
pyvallocation/__init__.py
pyvallocation/bayesian.py
pyvallocation/discrete_allocation.py
pyvallocation/ensembles.py
pyvallocation/moments.py
pyvallocation/optimization.py
pyvallocation/plotting.py
pyvallocation/portfolioapi.py
pyvallocation/probabilities.py
pyvallocation/stress.py
pyvallocation/views.py
pyvallocation/utils/__init__.py
pyvallocation/utils/constraints.py
pyvallocation/utils/data_helpers.py
pyvallocation/utils/functions.py
pyvallocation/utils/performance.py
pyvallocation/utils/projection.py
pyvallocation/utils/validation.py
pyvallocation/utils/weights.py
py_vallocation-0.3.1.dist-info/METADATA
py_vallocation-0.3.1.dist-info/WHEEL
py_vallocation-0.3.1.dist-info/top_level.txt
py_vallocation-0.3.1.dist-info/RECORD
