Metadata-Version: 2.4
Name: py-vallocation
Version: 0.3.1
Summary: Portfolio allocation tools with views, robust optimization, and ensembling
Author: enexqnt
License: GPL-3.0-or-later
Project-URL: Homepage, https://github.com/enexqnt/py-vallocation
Project-URL: Documentation, https://py-vallocation.readthedocs.io
Project-URL: Repository, https://github.com/enexqnt/py-vallocation
Project-URL: Bug Tracker, https://github.com/enexqnt/py-vallocation/issues
Keywords: asset-allocation,portfolio-optimization,entropy-pooling,Black-Litterman,robust-optimization,quantitative-finance,bayesian-inference
Classifier: Development Status :: 4 - Beta
Classifier: Intended Audience :: Financial and Insurance Industry
Classifier: Intended Audience :: Science/Research
Classifier: License :: OSI Approved :: GNU General Public License v3 or later (GPLv3+)
Classifier: Programming Language :: Python :: 3
Classifier: Programming Language :: Python :: 3.8
Classifier: Programming Language :: Python :: 3.9
Classifier: Programming Language :: Python :: 3.10
Classifier: Programming Language :: Python :: 3.11
Classifier: Programming Language :: Python :: 3.12
Classifier: Operating System :: OS Independent
Classifier: Topic :: Office/Business :: Financial :: Investment
Classifier: Topic :: Scientific/Engineering :: Mathematics
Requires-Python: >=3.8
License-File: LICENSE
Requires-Dist: numpy>=1.20.0
Requires-Dist: cvxopt>=1.2.0
Requires-Dist: pandas>=1.0.0
Requires-Dist: scipy>=1.10.0
Provides-Extra: robust
Requires-Dist: non-linear-shrinkage>=1.0.0; extra == "robust"
Dynamic: license-file
